LICENSE
README.md
setup.py
leopards/Q.py
leopards/Query.py
leopards/__init__.py
leopards.egg-info/PKG-INFO
leopards.egg-info/SOURCES.txt
leopards.egg-info/dependency_links.txt
leopards.egg-info/not-zip-safe
leopards.egg-info/top_level.txt
tests/__init__.py
tests/test_file.py
tests/test_leopards.py