Metadata-Version: 2.1
Name: leopards
Version: 1.0.0
Summary: Allows filtering & aggregation iterable of dictionary by another dictionary. Much faster than pandas
Home-page: https://github.com/mkalioby/leopards/
Download-URL: https://github.com/mkalioby/leopards/
Author: Mohamed El-Kalioby
Author-email: mkalioby@mkalioby.com
License: MIT
Classifier: Development Status :: 5 - Production/Stable
Classifier: Intended Audience :: Developers
Classifier: Operating System :: OS Independent
Classifier: Programming Language :: Python
Classifier: Programming Language :: Python :: 3
Classifier: Programming Language :: Python :: 3.7
Classifier: Programming Language :: Python :: 3.8
Classifier: Programming Language :: Python :: 3.9
Classifier: Programming Language :: Python :: 3.10
Classifier: Programming Language :: Python :: 3.11
Classifier: Programming Language :: Python :: 3.12
Classifier: Programming Language :: Python :: 3.13
Classifier: Topic :: Software Development :: Libraries :: Python Modules
Requires-Python: >=3.7
License-File: LICENSE
